covidpy/__init__.py
covidpy-0.1.4.dist-info/LICENSE
covidpy-0.1.4.dist-info/METADATA
covidpy-0.1.4.dist-info/WHEEL
covidpy-0.1.4.dist-info/top_level.txt
covidpy-0.1.4.dist-info/RECORD
